cl/__init__.py
cl/__main__.py
cl/asr_models/__init__.py
cl/asr_models/asr_aku.py
cl/asr_models/asr_base.py
cl/asr_models/asr_w2v2.py
cl/base_asr_model.py
cl/batch.py
cl/classes.py
cl/cli_dispatcher.py
cl/curriculum.py
cl/examples/hyperparameters.yaml
cl/examples/train.py
cl/filelist_tokenizer.py
cl/hparams_examples/base_recipe.yaml
cl/info/__init__.py
cl/info/find_anomalies.py
cl/info/get_train_times.py
cl/info/globals.py
cl/info/log_corr.py
cl/info/plot_metric_per_length.py
cl/info/read_wer_test.py
cl/info/statmd.py
cl/info/test_scores.py
cl/info/testset_correlation.py
cl/info/time_stats.py
cl/info/visualize.py
cl/methods/frequency_cl.py
cl/py.typed
cl/train_utlis.py
cl/utils/__init__.py
cl/utils/convert_txt_to_trn.py
cl/utils/kaldi_format_calc_wer.py
cl/utils/process_significance_tests.py
cl/utils/process_utils.py
cl/utils/remove_repetitions.py
cl/utils/sb_wer_to_kaldi.py
cl/utils/significance_tests.py
cl/utils/significance_tests.sh
cl/vad/data_augment.py
cl/vad/hparams/train.yaml
cl/vad/train.py
cl/vad.py
speechbrain_cl-1.0.1a0.dist-info/entry_points.txt
speechbrain_cl-1.0.1a0.dist-info/LICENSE
speechbrain_cl-1.0.1a0.dist-info/WHEEL
speechbrain_cl-1.0.1a0.dist-info/METADATA
speechbrain_cl-1.0.1a0.dist-info/RECORD
