Metadata-Version: 2.1
Name: speechbrain-cl
Version: 1.0.1a0
Summary: Implementation of multiple curriculum learning methods for speechbrain ASR (mirror from private repo).
Home-page: https://github.com/geoph9/speechbrain-cl
License: MIT
Keywords: curriculum-learning,speechbrain,speech-recognition
Author: Georgios K.
Author-email: geoph9@protonmail.com
Requires-Python: >=3.8,<3.10
Classifier: Development Status :: 2 - Pre-Alpha
Classifier: License :: OSI Approved :: MIT License
Classifier: Programming Language :: Python :: 3
Classifier: Programming Language :: Python :: 3.8
Classifier: Programming Language :: Python :: 3.9
Requires-Dist: pandas (>=1.4.0,<1.5.0)
Requires-Dist: pre-commit (>=2.3.0)
Requires-Dist: speechbrain-geoph9 (==0.5.12a0)
Requires-Dist: transformers (==4.4.0)
Project-URL: Changelog, https://github.com/geoph9/speechbrain-cl/releases
Project-URL: Documentation, https://speechbrain-cl.readthedocs.io
Project-URL: Repository, https://github.com/geoph9/speechbrain-cl
